safe/__init__.py
safe/decorator.py
safe/py.typed
safe/typing.py
safe/utils.py
safe_returns-0.2.0.dist-info/METADATA
safe_returns-0.2.0.dist-info/WHEEL
safe_returns-0.2.0.dist-info/licenses/LICENSE
safe_returns-0.2.0.dist-info/RECORD
