Metadata-Version: 2.3
Name: safe-returns
Version: 0.2.0
Summary: Safe returns function decorator
Project-URL: Repository, https://github.com/feodor-ra/safe-returns
Project-URL: Homepage, https://github.com/feodor-ra/safe-returns
Project-URL: Documentation, https://feodor-ra.github.io/safe-returns/
Author-email: Fedor Ratschew <feodor.ra@me.com>
Classifier: Development Status :: 5 - Production/Stable
Classifier: License :: OSI Approved :: MIT License
Classifier: Programming Language :: Python :: 3.11
Classifier: Programming Language :: Python :: 3.12
Classifier: Programming Language :: Python :: 3.13
Classifier: Topic :: Utilities
Requires-Python: >=3.11
